{
  "abi_covariance_summary": {},
  "abi_drift_from_parent": 0.0,
  "abi_mean_norm": null,
  "average_sequence_length": 15.0,
  "byte_count": 15,
  "byte_entropy": 3.1395723819732666,
  "byte_histogram_summary": {
    "top_bytes": [
      {
        "byte": 101,
        "count": 3
      },
      {
        "byte": 108,
        "count": 3
      },
      {
        "byte": 97,
        "count": 2
      },
      {
        "byte": 32,
        "count": 1
      },
      {
        "byte": 107,
        "count": 1
      },
      {
        "byte": 114,
        "count": 1
      },
      {
        "byte": 104,
        "count": 1
      },
      {
        "byte": 121,
        "count": 1
      }
    ],
    "unique_bytes": 10
  },
  "byte_transformer_baseline_bpb": null,
  "code_symbol_rate": 0.0,
  "created_at": "2026-06-24T02:23:54.098165+00:00",
  "current_model_bpb": null,
  "current_model_loss": null,
  "dataset_manifest_hash": "91c5e043bf6fd67f44ce4f721823c2fb391332fc2b0c7f8ba1dae8174411443e",
  "difficulty_buckets": [
    {
      "byte_count": 15,
      "difficulty": 3.1395723819732666,
      "index": 0
    }
  ],
  "estimated_train_steps": 2,
  "estimated_trainable_params": 0,
  "estimated_wallclock_proxy": 3e-08,
  "input_mode": "bytes",
  "parent_commit_id": "9dc7ad1a9b6a24b4",
  "patch_compression_ratio": 1.875,
  "patch_count": 8,
  "patching_mode": "fixed:2",
  "preview_hash": "6c7b21c8fd43f930dfc6a10a41a31b3a246841c23dda2f50802b6444ef090282",
  "preview_id": "d698f4223ec9c375",
  "rare_byte_rate": 0.4666666666666667,
  "recommended_curriculum": "easy_to_hard",
  "recommended_frozen_modules": [],
  "recommended_gates": [
    {
      "metric": "score",
      "threshold": 0.5,
      "type": "min_metric"
    }
  ],
  "recommended_loss_weights": {
    "abi_stability": 0.1,
    "lm": 1.0
  },
  "recommended_trainable_modules": [
    "layercake_core"
  ],
  "rubric_id": "pg",
  "sample_count": 1,
  "token_count": null,
  "transformer_baseline_bpb": null,
  "unicode_rate": 0.0,
  "warnings": []
}
